source/__init__.py
source/cli.py
source/helpers.py
source/utilities/__init__.py
source/utilities/csv/__init__.py
source/utilities/csv/cli.py
source/utilities/csv/merge_columns.py
source/utilities/csv/remove_column.py
source/utilities/csv/remove_nulls.py
source/utilities/csv/shift_column.py
source/utilities/csv/split.py
source/utilities/csv/validate.py
source/utilities/ndjson/__init__.py
source/utilities/ndjson/cli.py
source/utilities/ndjson/merge_keys.py
source/utilities/ndjson/remove_key.py
source/utilities/ndjson/validate.py
pycli_utilities-1.1.0.dist-info/LICENSE
pycli_utilities-1.1.0.dist-info/METADATA
pycli_utilities-1.1.0.dist-info/WHEEL
pycli_utilities-1.1.0.dist-info/entry_points.txt
pycli_utilities-1.1.0.dist-info/top_level.txt
pycli_utilities-1.1.0.dist-info/RECORD
