Metadata-Version: 2.1
Name: pycli-utilities
Version: 1.1.0
Summary: pyCLI Utilities
Home-page: https://github.com/itsthevp/pycli-utilities
Author: Vishv Patel (itsthevp)
License: MIT
Keywords: cli,utils,cli-utils,csv,json
Classifier: License :: OSI Approved :: MIT License
Classifier: Programming Language :: Python
Classifier: Programming Language :: Python :: 3
Classifier: Programming Language :: Python :: 3.6
Classifier: Programming Language :: Python :: Implementation :: CPython
Requires-Python: >=3.6.0
License-File: LICENSE
